[
  {
    "ContainingType": "PechkovDenisKt_42_22.Controllers.DepartmentsController",
    "Method": "GetDepartments",
    "RelativePath": "api/Departments",
    "HttpMethod": "GET",
    "IsController": true,
    "Order": 0,
    "Parameters": [
      {
        "Name": "foundedAfter",
        "Type": "System.Nullable\u00601[[System.DateTime, System.Private.CoreLib, Version=6.0.0.0, Culture=neutral, PublicKeyToken=7cec85d7bea7798e]]",
        "IsRequired": false
      },
      {
        "Name": "minTeacherCount",
        "Type": "System.Nullable\u00601[[System.Int32, System.Private.CoreLib, Version=6.0.0.0, Culture=neutral, PublicKeyToken=7cec85d7bea7798e]]",
        "IsRequired": false
      }
    ],
    "ReturnTypes": []
  },
  {
    "ContainingType": "PechkovDenisKt_42_22.Controllers.DepartmentsController",
    "Method": "AddDepartment",
    "RelativePath": "api/Departments",
    "HttpMethod": "POST",
    "IsController": true,
    "Order": 0,
    "Parameters": [
      {
        "Name": "createDepartmentDto",
        "Type": "PechkovDenisKt_42_22.Models.DTO.CreateDepartmentDto",
        "IsRequired": true
      }
    ],
    "ReturnTypes": []
  },
  {
    "ContainingType": "PechkovDenisKt_42_22.Controllers.DepartmentsController",
    "Method": "UpdateDepartment",
    "RelativePath": "api/Departments/{id}",
    "HttpMethod": "PUT",
    "IsController": true,
    "Order": 0,
    "Parameters": [
      {
        "Name": "id",
        "Type": "System.Int32",
        "IsRequired": true
      },
      {
        "Name": "updateDepartmentDto",
        "Type": "PechkovDenisKt_42_22.Models.DTO.UpdateDepartmentDto",
        "IsRequired": true
      }
    ],
    "ReturnTypes": []
  },
  {
    "ContainingType": "PechkovDenisKt_42_22.Controllers.DepartmentsController",
    "Method": "DeleteDepartment",
    "RelativePath": "api/Departments/{id}",
    "HttpMethod": "DELETE",
    "IsController": true,
    "Order": 0,
    "Parameters": [
      {
        "Name": "id",
        "Type": "System.Int32",
        "IsRequired": true
      }
    ],
    "ReturnTypes": []
  },
  {
    "ContainingType": "PechkovDenisKt_42_22.Controllers.DisciplinesController",
    "Method": "GetDisciplines",
    "RelativePath": "api/Disciplines",
    "HttpMethod": "GET",
    "IsController": true,
    "Order": 0,
    "Parameters": [
      {
        "Name": "firstName",
        "Type": "System.String",
        "IsRequired": false
      },
      {
        "Name": "lastName",
        "Type": "System.String",
        "IsRequired": false
      },
      {
        "Name": "minHours",
        "Type": "System.Nullable\u00601[[System.Int32, System.Private.CoreLib, Version=6.0.0.0, Culture=neutral, PublicKeyToken=7cec85d7bea7798e]]",
        "IsRequired": false
      },
      {
        "Name": "maxHours",
        "Type": "System.Nullable\u00601[[System.Int32, System.Private.CoreLib, Version=6.0.0.0, Culture=neutral, PublicKeyToken=7cec85d7bea7798e]]",
        "IsRequired": false
      }
    ],
    "ReturnTypes": []
  },
  {
    "ContainingType": "PechkovDenisKt_42_22.Controllers.DisciplinesController",
    "Method": "AddDiscipline",
    "RelativePath": "api/Disciplines",
    "HttpMethod": "POST",
    "IsController": true,
    "Order": 0,
    "Parameters": [
      {
        "Name": "disciplineDto",
        "Type": "PechkovDenisKt_42_22.Models.DTO.DisciplineDto",
        "IsRequired": true
      }
    ],
    "ReturnTypes": []
  },
  {
    "ContainingType": "PechkovDenisKt_42_22.Controllers.DisciplinesController",
    "Method": "GetDisciplineById",
    "RelativePath": "api/Disciplines/{id}",
    "HttpMethod": "GET",
    "IsController": true,
    "Order": 0,
    "Parameters": [
      {
        "Name": "id",
        "Type": "System.Int32",
        "IsRequired": true
      }
    ],
    "ReturnTypes": []
  },
  {
    "ContainingType": "PechkovDenisKt_42_22.Controllers.DisciplinesController",
    "Method": "UpdateDiscipline",
    "RelativePath": "api/Disciplines/{id}",
    "HttpMethod": "PUT",
    "IsController": true,
    "Order": 0,
    "Parameters": [
      {
        "Name": "id",
        "Type": "System.Int32",
        "IsRequired": true
      },
      {
        "Name": "disciplineDto",
        "Type": "PechkovDenisKt_42_22.Models.DTO.DisciplineDto",
        "IsRequired": true
      }
    ],
    "ReturnTypes": []
  },
  {
    "ContainingType": "PechkovDenisKt_42_22.Controllers.DisciplinesController",
    "Method": "DeleteDiscipline",
    "RelativePath": "api/Disciplines/{id}",
    "HttpMethod": "DELETE",
    "IsController": true,
    "Order": 0,
    "Parameters": [
      {
        "Name": "id",
        "Type": "System.Int32",
        "IsRequired": true
      }
    ],
    "ReturnTypes": []
  },
  {
    "ContainingType": "PechkovDenisKt_42_22.Controllers.LoadsController",
    "Method": "GetLoads",
    "RelativePath": "api/Loads",
    "HttpMethod": "GET",
    "IsController": true,
    "Order": 0,
    "Parameters": [
      {
        "Name": "teacherFirstName",
        "Type": "System.String",
        "IsRequired": false
      },
      {
        "Name": "teacherLastName",
        "Type": "System.String",
        "IsRequired": false
      },
      {
        "Name": "departmentName",
        "Type": "System.String",
        "IsRequired": false
      },
      {
        "Name": "disciplineName",
        "Type": "System.String",
        "IsRequired": false
      }
    ],
    "ReturnTypes": []
  },
  {
    "ContainingType": "PechkovDenisKt_42_22.Controllers.LoadsController",
    "Method": "AddLoad",
    "RelativePath": "api/Loads",
    "HttpMethod": "POST",
    "IsController": true,
    "Order": 0,
    "Parameters": [
      {
        "Name": "loadDto",
        "Type": "PechkovDenisKt_42_22.Models.DTO.LoadDto",
        "IsRequired": true
      }
    ],
    "ReturnTypes": []
  },
  {
    "ContainingType": "PechkovDenisKt_42_22.Controllers.LoadsController",
    "Method": "UpdateLoad",
    "RelativePath": "api/Loads/{id}",
    "HttpMethod": "PUT",
    "IsController": true,
    "Order": 0,
    "Parameters": [
      {
        "Name": "id",
        "Type": "System.Int32",
        "IsRequired": true
      },
      {
        "Name": "loadDto",
        "Type": "PechkovDenisKt_42_22.Models.DTO.LoadDto",
        "IsRequired": true
      }
    ],
    "ReturnTypes": []
  },
  {
    "ContainingType": "PechkovDenisKt_42_22.Controllers.TeachersController",
    "Method": "GetTeachers",
    "RelativePath": "api/Teachers",
    "HttpMethod": "GET",
    "IsController": true,
    "Order": 0,
    "Parameters": [
      {
        "Name": "departmentName",
        "Type": "System.String",
        "IsRequired": false
      },
      {
        "Name": "degreeName",
        "Type": "System.String",
        "IsRequired": false
      },
      {
        "Name": "positionName",
        "Type": "System.String",
        "IsRequired": false
      }
    ],
    "ReturnTypes": []
  },
  {
    "ContainingType": "PechkovDenisKt_42_22.Controllers.TeachersController",
    "Method": "AddTeacher",
    "RelativePath": "api/Teachers",
    "HttpMethod": "POST",
    "IsController": true,
    "Order": 0,
    "Parameters": [
      {
        "Name": "teacherDto",
        "Type": "PechkovDenisKt_42_22.Models.DTO.TeacherDto",
        "IsRequired": true
      }
    ],
    "ReturnTypes": []
  },
  {
    "ContainingType": "PechkovDenisKt_42_22.Controllers.TeachersController",
    "Method": "GetTeacherById",
    "RelativePath": "api/Teachers/{id}",
    "HttpMethod": "GET",
    "IsController": true,
    "Order": 0,
    "Parameters": [
      {
        "Name": "id",
        "Type": "System.Int32",
        "IsRequired": true
      }
    ],
    "ReturnTypes": [
      {
        "Type": "PechkovDenisKt_42_22.Models.Teacher",
        "MediaTypes": [
          "text/plain",
          "application/json",
          "text/json"
        ],
        "StatusCode": 200
      }
    ]
  },
  {
    "ContainingType": "PechkovDenisKt_42_22.Controllers.TeachersController",
    "Method": "UpdateTeacher",
    "RelativePath": "api/Teachers/{id}",
    "HttpMethod": "PUT",
    "IsController": true,
    "Order": 0,
    "Parameters": [
      {
        "Name": "id",
        "Type": "System.Int32",
        "IsRequired": true
      },
      {
        "Name": "teacherDto",
        "Type": "PechkovDenisKt_42_22.Models.DTO.TeacherDto",
        "IsRequired": true
      }
    ],
    "ReturnTypes": []
  },
  {
    "ContainingType": "PechkovDenisKt_42_22.Controllers.TeachersController",
    "Method": "DeleteTeacher",
    "RelativePath": "api/Teachers/{id}",
    "HttpMethod": "DELETE",
    "IsController": true,
    "Order": 0,
    "Parameters": [
      {
        "Name": "id",
        "Type": "System.Int32",
        "IsRequired": true
      }
    ],
    "ReturnTypes": []
  },
  {
    "ContainingType": "PechkovDenisKt_42_22.Controllers.WeatherForecastController",
    "Method": "Get",
    "RelativePath": "WeatherForecast",
    "HttpMethod": "GET",
    "IsController": true,
    "Order": 0,
    "Parameters": [],
    "ReturnTypes": [
      {
        "Type": "System.Collections.Generic.IEnumerable\u00601[[PechkovDenisKt_42_22.WeatherForecast, PechkovDenisKt-42-22, Version=1.0.0.0, Culture=neutral, PublicKeyToken=null]]",
        "MediaTypes": [
          "text/plain",
          "application/json",
          "text/json"
        ],
        "StatusCode": 200
      }
    ],
    "EndpointName": "GetWeatherForecast"
  },
  {
    "ContainingType": "PechkovDenisKt_42_22.Controllers.WeatherForecastController",
    "Method": "AddNewSummary",
    "RelativePath": "WeatherForecast",
    "HttpMethod": "POST",
    "IsController": true,
    "Order": 0,
    "Parameters": [
      {
        "Name": "newSummary",
        "Type": "System.String",
        "IsRequired": false
      }
    ],
    "ReturnTypes": [
      {
        "Type": "System.String[]",
        "MediaTypes": [
          "text/plain",
          "application/json",
          "text/json"
        ],
        "StatusCode": 200
      }
    ],
    "EndpointName": "AddNewSummary"
  }
]